src/RequestHandler.py
src/SharePointHandler.py
src/TableLogHandler.py
src/__init__.py
src/brzGlobal.py
src/gbtGlobal.py
src/mstAst.py
src/mstLog.py
cumulus_kern-0.0.2.dist-info/LICENSE
cumulus_kern-0.0.2.dist-info/METADATA
cumulus_kern-0.0.2.dist-info/WHEEL
cumulus_kern-0.0.2.dist-info/top_level.txt
cumulus_kern-0.0.2.dist-info/RECORD
