Metadata-Version: 2.1
Name: cumulus-kern
Version: 0.0.2
Summary: Kernel functions for Cumulus
Home-page: https://github.com/nino-baywa/cumulus_kern
Author: BayWa r.e. Data Services GmbH
Author-email: no-reply@baywa-re.com
Project-URL: repository, https://github.com/nino-baywa/cumulus_kern
Classifier: Programming Language :: Python :: 3
Classifier: Operating System :: OS Independent
Requires-Python: >=3.8
License-File: LICENSE
